setup.cfg
setup.py
provtool/__init__.py
provtool/cli.py
provtool.egg-info/PKG-INFO
provtool.egg-info/SOURCES.txt
provtool.egg-info/dependency_links.txt
provtool.egg-info/entry_points.txt
provtool.egg-info/not-zip-safe
provtool.egg-info/top_level.txt