Metadata-Version: 1.0
Name: provtool
Version: 0.3.0
Summary: Utility for working with iOS Provisioning Profiles
Home-page: UNKNOWN
Author: Andy Mroczkowski
Author-email: andy@mindsnacks.com
License: BSD
Keywords: ios provisioning
Platform: UNKNOWN
